README.md
setup.py
cheesefactory_database/__init__.py
cheesefactory_database/mssql.py
cheesefactory_database/postgresql.py
cheesefactory_database.egg-info/PKG-INFO
cheesefactory_database.egg-info/SOURCES.txt
cheesefactory_database.egg-info/dependency_links.txt
cheesefactory_database.egg-info/requires.txt
cheesefactory_database.egg-info/top_level.txt