Metadata-Version: 2.1
Name: cheesefactory-database
Version: 0.8
Summary: Wrappers for PostgreSQL interaction using dataframes or dictionaries.
Home-page: https://bitbucket.org/hellsgrannies/cheesefactory-database
Author: Todd Salazar
Author-email: unixsal@yahoo.com
License: UNKNOWN
Keywords: cheesefactory database postgresql postgres development pandas dataframe
Platform: UNKNOWN
Classifier: Development Status :: 4 - Beta
Classifier: Intended Audience :: Developers
Classifier: License :: OSI Approved :: BSD License
Classifier: Programming Language :: Python :: 3.6
Classifier: Programming Language :: Python :: 3.7
Classifier: Programming Language :: Python :: 3.8
